AssetAllocator/__init__.py
AssetAllocator/experiment.py
AssetAllocator/trainer.py
AssetAllocator/algorithms/__init__.py
AssetAllocator/algorithms/A2C/__init__.py
AssetAllocator/algorithms/A2C/a2c.py
AssetAllocator/algorithms/A2C/agent.py
AssetAllocator/algorithms/Baselines/__init__.py
AssetAllocator/algorithms/Baselines/agent.py
AssetAllocator/algorithms/Baselines/mpt.py
AssetAllocator/algorithms/DDPG/DDPG.py
AssetAllocator/algorithms/DDPG/Network.py
AssetAllocator/algorithms/DDPG/OU_Noise.py
AssetAllocator/algorithms/DDPG/Replay_Memory.py
AssetAllocator/algorithms/DDPG/__init__.py
AssetAllocator/algorithms/DDPG/agent.py
AssetAllocator/algorithms/NAF/__init__.py
AssetAllocator/algorithms/NAF/agent.py
AssetAllocator/algorithms/NAF/network.py
AssetAllocator/algorithms/NAF/noise.py
AssetAllocator/algorithms/NAF/replay_buffer.py
AssetAllocator/algorithms/PPO/__init__.py
AssetAllocator/algorithms/PPO/agent.py
AssetAllocator/algorithms/PPO/eval_policy.py
AssetAllocator/algorithms/PPO/network.py
AssetAllocator/algorithms/REINFORCE/__init__.py
AssetAllocator/algorithms/REINFORCE/agent.py
AssetAllocator/algorithms/REINFORCE/normalized_actions.py
AssetAllocator/algorithms/REINFORCE/reinforce_continuous.py
AssetAllocator/algorithms/SAC/SAC.py
AssetAllocator/algorithms/SAC/__init__.py
AssetAllocator/algorithms/SAC/agent.py
AssetAllocator/algorithms/TD3/__init__.py
AssetAllocator/algorithms/TD3/actor.py
AssetAllocator/algorithms/TD3/agent.py
AssetAllocator/algorithms/TD3/critic.py
AssetAllocator/algorithms/TD3/memory.py
AssetAllocator/algorithms/TRPO/__init__.py
AssetAllocator/algorithms/TRPO/agent.py
AssetAllocator/algorithms/TRPO/policy.py
AssetAllocator/algorithms/TRPO/trpo.py
AssetAllocator/algorithms/TRPO/utils.py
AssetAllocator/algorithms/TRPO/value.py
AssetAllocator/config/__init__.py
AssetAllocator/config/tickers.py
AssetAllocator/data/Big4.csv
AssetAllocator/data/DOW30.csv
AssetAllocator/data/__init__.py
AssetAllocator/data/datasets.py
AssetAllocator-0.0.12.dist-info/METADATA
AssetAllocator-0.0.12.dist-info/WHEEL
AssetAllocator-0.0.12.dist-info/top_level.txt
AssetAllocator-0.0.12.dist-info/RECORD
